README.txt
setup.py
qi/__init__.py
qi.GRSplitter.egg-info/PKG-INFO
qi.GRSplitter.egg-info/SOURCES.txt
qi.GRSplitter.egg-info/dependency_links.txt
qi.GRSplitter.egg-info/entry_points.txt
qi.GRSplitter.egg-info/namespace_packages.txt
qi.GRSplitter.egg-info/not-zip-safe
qi.GRSplitter.egg-info/requires.txt
qi.GRSplitter.egg-info/top_level.txt
qi/GRSplitter/GRSplitter.py
qi/GRSplitter/__init__.py
qi/GRSplitter/configure.zcml
qi/GRSplitter/tests.py
qi/GRSplitter/zope2.py