Metadata-Version: 1.0
Name: qi.GRSplitter
Version: 1.1.1
Summary: Greek word splitter for ZCTextIndex
Home-page: http://svn.plone.org/svn/collective/qi.GRSplitter
Author: G. Gozadinos
Author-email: ggozad@qiweb.net
License: GPL
Keywords: plone zope greek ZCTextIndex Splitter
Platform: UNKNOWN
Classifier: Programming Language :: Python
Classifier: Topic :: Software Development :: Libraries :: Python Modules
